jobtimize/__init__.py
jobtimize/scrapers/__init__.py
jobtimize/scrapers/main.py
jobtimize/scrapers/rotateproxies.py
jobtimize/scrapers/scrapindeed.py
jobtimize/scrapers/scrapmonster.py
Jobtimize-0.0.5a2.dist-info/LICENSE
Jobtimize-0.0.5a2.dist-info/METADATA
Jobtimize-0.0.5a2.dist-info/WHEEL
Jobtimize-0.0.5a2.dist-info/top_level.txt
Jobtimize-0.0.5a2.dist-info/RECORD
