Metadata-Version: 2.1
Name: Jobtimize
Version: 0.0.5a2
Summary: Collect and standardize data on job posting platforms.
Home-page: https://loicrakotoson.com/Jobtimize/
Author: Loïc Rakotoson
Author-email: contact@loicrakotoson.com
License: MIT
Platform: UNKNOWN
Classifier: License :: OSI Approved :: MIT License
Classifier: Development Status :: 3 - Alpha
Classifier: Natural Language :: English
Classifier: Operating System :: OS Independent
Classifier: Programming Language :: Python :: 3
Classifier: Programming Language :: Python :: 3.6
Classifier: Programming Language :: Python :: 3.7
Classifier: Topic :: Utilities
Classifier: Topic :: Database
Classifier: Topic :: Education
Classifier: Topic :: Internet :: WWW/HTTP :: Indexing/Search
Classifier: Operating System :: OS Independent
Requires-Python: >=3.6
Requires-Dist: beautifulsoup4
Requires-Dist: pandas
Requires-Dist: jsonschema
Requires-Dist: lxml
Requires-Dist: requests
